{
  "Data": [
    {
      "idData": "U001",
      "Points": 0,
      "History": [
        {
          "language": "cpp",
          "problem": "A1",
          "status": true,
          "summary": {
            "max_time_ms": 26,
            "max_memory_kb": 256
          },
          "time": "2025-08-11T02:59:06.538Z",
          "resultDescription": "❌ RTE — Runtime Error",
          "problemName": "Tính Giai Thừa",
          "maxPoints": 0
        },
        {
          "language": "cpp",
          "problem": "A1",
          "status": true,
          "summary": {
            "max_time_ms": 30,
            "max_memory_kb": 256
          },
          "time": "2025-08-11T02:59:04.033Z",
          "resultDescription": "❌ RTE — Runtime Error",
          "problemName": "Tính Giai Thừa",
          "maxPoints": 0
        },
        {
          "language": "cpp",
          "problem": "A1",
          "status": true,
          "summary": {
            "max_time_ms": 26,
            "max_memory_kb": 256
          },
          "time": "2025-08-11T02:59:01.671Z",
          "resultDescription": "❌ RTE — Runtime Error",
          "problemName": "Tính Giai Thừa",
          "maxPoints": 0
        },
        {
          "language": "cpp",
          "problem": "A1",
          "status": true,
          "summary": {
            "max_time_ms": 25,
            "max_memory_kb": 256
          },
          "time": "2025-08-11T02:58:59.337Z",
          "resultDescription": "❌ RTE — Runtime Error",
          "problemName": "Tính Giai Thừa",
          "maxPoints": 0
        },
        {
          "language": "cpp",
          "problem": "A1",
          "status": true,
          "summary": {
            "max_time_ms": 34,
            "max_memory_kb": 256
          },
          "time": "2025-08-11T02:58:53.084Z",
          "resultDescription": "❌ RTE — Runtime Error",
          "problemName": "Tính Giai Thừa",
          "maxPoints": 0
        },
        {
          "language": "cpp",
          "problem": "A1",
          "status": true,
          "summary": {
            "max_time_ms": 32,
            "max_memory_kb": 256
          },
          "time": "2025-08-11T02:58:50.745Z",
          "resultDescription": "❌ RTE — Runtime Error",
          "problemName": "Tính Giai Thừa",
          "maxPoints": 0
        },
        {
          "language": "cpp",
          "problem": "A1",
          "status": true,
          "summary": {
            "max_time_ms": 26,
            "max_memory_kb": 256
          },
          "time": "2025-08-11T02:58:46.265Z",
          "resultDescription": "❌ RTE — Runtime Error",
          "problemName": "Tính Giai Thừa",
          "maxPoints": 0
        },
        {
          "language": "cpp",
          "problem": "A1",
          "status": true,
          "summary": {
            "max_time_ms": 36,
            "max_memory_kb": 256
          },
          "time": "2025-08-11T02:58:43.818Z",
          "resultDescription": "❌ RTE — Runtime Error",
          "problemName": "Tính Giai Thừa",
          "maxPoints": 0
        },
        {
          "language": "cpp",
          "problem": "A1",
          "status": true,
          "summary": {
            "max_time_ms": 18,
            "max_memory_kb": 256
          },
          "time": "2025-08-11T02:58:40.302Z",
          "resultDescription": "❌ RTE — Runtime Error",
          "problemName": "Tính Giai Thừa",
          "maxPoints": 0
        },
        {
          "language": "cpp",
          "problem": "A1",
          "status": true,
          "summary": {
            "max_time_ms": 32,
            "max_memory_kb": 256
          },
          "time": "2025-08-11T02:58:36.688Z",
          "resultDescription": "❌ RTE — Runtime Error",
          "problemName": "Tính Giai Thừa",
          "maxPoints": 0
        },
        {
          "language": "cpp",
          "problem": "A1",
          "status": true,
          "summary": {
            "max_time_ms": 33,
            "max_memory_kb": 256
          },
          "time": "2025-08-11T02:58:33.990Z",
          "resultDescription": "❌ RTE — Runtime Error",
          "problemName": "Tính Giai Thừa",
          "maxPoints": 0
        },
        {
          "language": "cpp",
          "problem": "A1",
          "status": true,
          "summary": {
            "max_time_ms": 23,
            "max_memory_kb": 256
          },
          "time": "2025-08-11T02:58:31.056Z",
          "resultDescription": "❌ RTE — Runtime Error",
          "problemName": "Tính Giai Thừa",
          "maxPoints": 0
        },
        {
          "language": "cpp",
          "problem": "A1",
          "status": true,
          "summary": {
            "max_time_ms": 32,
            "max_memory_kb": 256
          },
          "time": "2025-08-11T02:58:28.546Z",
          "resultDescription": "❌ RTE — Runtime Error",
          "problemName": "Tính Giai Thừa",
          "maxPoints": 0
        },
        {
          "language": "cpp",
          "problem": "A1",
          "status": true,
          "summary": {
            "max_time_ms": 29,
            "max_memory_kb": 256
          },
          "time": "2025-08-11T02:58:25.604Z",
          "resultDescription": "❌ RTE — Runtime Error",
          "problemName": "Tính Giai Thừa",
          "maxPoints": 0
        },
        {
          "language": "cpp",
          "problem": "A1",
          "status": true,
          "summary": {
            "max_time_ms": 28,
            "max_memory_kb": 256
          },
          "time": "2025-08-11T02:58:22.688Z",
          "resultDescription": "❌ RTE — Runtime Error",
          "problemName": "Tính Giai Thừa",
          "maxPoints": 0
        },
        {
          "language": "cpp",
          "problem": "A1",
          "status": true,
          "summary": {
            "max_time_ms": 27,
            "max_memory_kb": 256
          },
          "time": "2025-08-11T02:58:20.415Z",
          "resultDescription": "❌ RTE — Runtime Error",
          "problemName": "Tính Giai Thừa",
          "maxPoints": 0
        },
        {
          "language": "cpp",
          "problem": "A1",
          "status": true,
          "summary": {
            "max_time_ms": 33,
            "max_memory_kb": 256
          },
          "time": "2025-08-11T02:58:17.940Z",
          "resultDescription": "❌ RTE — Runtime Error",
          "problemName": "Tính Giai Thừa",
          "maxPoints": 0
        },
        {
          "language": "cpp",
          "problem": "A1",
          "status": true,
          "summary": {
            "max_time_ms": 23,
            "max_memory_kb": 256
          },
          "time": "2025-08-11T02:58:15.741Z",
          "resultDescription": "❌ RTE — Runtime Error",
          "problemName": "Tính Giai Thừa",
          "maxPoints": 0
        },
        {
          "language": "cpp",
          "problem": "A1",
          "status": true,
          "summary": {
            "max_time_ms": 36,
            "max_memory_kb": 256
          },
          "time": "2025-08-11T02:58:13.425Z",
          "resultDescription": "❌ RTE — Runtime Error",
          "problemName": "Tính Giai Thừa",
          "maxPoints": 0
        },
        {
          "language": "cpp",
          "problem": "A1",
          "status": true,
          "summary": {
            "max_time_ms": 31,
            "max_memory_kb": 256
          },
          "time": "2025-08-11T02:58:11.238Z",
          "resultDescription": "❌ RTE — Runtime Error",
          "problemName": "Tính Giai Thừa",
          "maxPoints": 0
        },
        {
          "language": "cpp",
          "problem": "A1",
          "status": true,
          "summary": {
            "max_time_ms": 29,
            "max_memory_kb": 256
          },
          "time": "2025-08-11T02:58:08.776Z",
          "resultDescription": "❌ RTE — Runtime Error",
          "problemName": "Tính Giai Thừa",
          "maxPoints": 0
        },
        {
          "language": "cpp",
          "problem": "A1",
          "status": true,
          "summary": {
            "max_time_ms": 29,
            "max_memory_kb": 256
          },
          "time": "2025-08-11T02:58:05.826Z",
          "resultDescription": "❌ RTE — Runtime Error",
          "problemName": "Tính Giai Thừa",
          "maxPoints": 0
        },
        {
          "language": "cpp",
          "problem": "A1",
          "status": true,
          "summary": {
            "max_time_ms": 31,
            "max_memory_kb": 256
          },
          "time": "2025-08-11T02:58:02.942Z",
          "resultDescription": "❌ RTE — Runtime Error",
          "problemName": "Tính Giai Thừa",
          "maxPoints": 0
        },
        {
          "language": "cpp",
          "problem": "A1",
          "status": true,
          "summary": {
            "max_time_ms": 24,
            "max_memory_kb": 256
          },
          "time": "2025-08-11T02:58:00.706Z",
          "resultDescription": "❌ RTE — Runtime Error",
          "problemName": "Tính Giai Thừa",
          "maxPoints": 0
        },
        {
          "language": "cpp",
          "problem": "A1",
          "status": true,
          "summary": {
            "max_time_ms": 24,
            "max_memory_kb": 256
          },
          "time": "2025-08-11T02:57:57.826Z",
          "resultDescription": "❌ RTE — Runtime Error",
          "problemName": "Tính Giai Thừa",
          "maxPoints": 0
        },
        {
          "language": "cpp",
          "problem": "A1",
          "status": true,
          "summary": {
            "max_time_ms": 22,
            "max_memory_kb": 256
          },
          "time": "2025-08-11T02:57:54.856Z",
          "resultDescription": "❌ RTE — Runtime Error",
          "problemName": "Tính Giai Thừa",
          "maxPoints": 0
        },
        {
          "language": "cpp",
          "problem": "A1",
          "status": true,
          "summary": {
            "max_time_ms": 27,
            "max_memory_kb": 256
          },
          "time": "2025-08-11T02:57:51.947Z",
          "resultDescription": "❌ RTE — Runtime Error",
          "problemName": "Tính Giai Thừa",
          "maxPoints": 0
        },
        {
          "language": "cpp",
          "problem": "A1",
          "status": true,
          "summary": {
            "max_time_ms": 30,
            "max_memory_kb": 256
          },
          "time": "2025-08-11T02:57:49.069Z",
          "resultDescription": "❌ RTE — Runtime Error",
          "problemName": "Tính Giai Thừa",
          "maxPoints": 0
        },
        {
          "language": "cpp",
          "problem": "A1",
          "status": true,
          "summary": {
            "max_time_ms": 23,
            "max_memory_kb": 256
          },
          "time": "2025-08-11T02:57:46.169Z",
          "resultDescription": "❌ RTE — Runtime Error",
          "problemName": "Tính Giai Thừa",
          "maxPoints": 0
        },
        {
          "language": "cpp",
          "problem": "A1",
          "status": true,
          "summary": {
            "max_time_ms": 43,
            "max_memory_kb": 256
          },
          "time": "2025-08-11T02:57:43.289Z",
          "resultDescription": "❌ RTE — Runtime Error",
          "problemName": "Tính Giai Thừa",
          "maxPoints": 0
        },
        {
          "language": "cpp",
          "problem": "A1",
          "status": true,
          "summary": {
            "max_time_ms": 24,
            "max_memory_kb": 256
          },
          "time": "2025-08-11T02:57:40.389Z",
          "resultDescription": "❌ RTE — Runtime Error",
          "problemName": "Tính Giai Thừa",
          "maxPoints": 0
        },
        {
          "language": "cpp",
          "problem": "A1",
          "status": true,
          "summary": {
            "max_time_ms": 22,
            "max_memory_kb": 256
          },
          "time": "2025-08-11T02:57:37.507Z",
          "resultDescription": "❌ RTE — Runtime Error",
          "problemName": "Tính Giai Thừa",
          "maxPoints": 0
        },
        {
          "language": "cpp",
          "problem": "A1",
          "status": true,
          "summary": {
            "max_time_ms": 30,
            "max_memory_kb": 256
          },
          "time": "2025-08-11T02:57:34.592Z",
          "resultDescription": "❌ RTE — Runtime Error",
          "problemName": "Tính Giai Thừa",
          "maxPoints": 0
        },
        {
          "language": "cpp",
          "problem": "A1",
          "status": true,
          "summary": {
            "max_time_ms": 22,
            "max_memory_kb": 256
          },
          "time": "2025-08-11T02:57:31.724Z",
          "resultDescription": "❌ RTE — Runtime Error",
          "problemName": "Tính Giai Thừa",
          "maxPoints": 0
        },
        {
          "language": "cpp",
          "problem": "A1",
          "status": true,
          "summary": {
            "max_time_ms": 24,
            "max_memory_kb": 256
          },
          "time": "2025-08-11T02:57:28.734Z",
          "resultDescription": "❌ RTE — Runtime Error",
          "problemName": "Tính Giai Thừa",
          "maxPoints": 0
        },
        {
          "language": "cpp",
          "problem": "A1",
          "status": true,
          "summary": {
            "max_time_ms": 25,
            "max_memory_kb": 256
          },
          "time": "2025-08-11T02:57:25.849Z",
          "resultDescription": "❌ RTE — Runtime Error",
          "problemName": "Tính Giai Thừa",
          "maxPoints": 0
        },
        {
          "language": "cpp",
          "problem": "A1",
          "status": true,
          "summary": {
            "max_time_ms": 30,
            "max_memory_kb": 256
          },
          "time": "2025-08-11T02:57:22.954Z",
          "resultDescription": "❌ RTE — Runtime Error",
          "problemName": "Tính Giai Thừa",
          "maxPoints": 0
        },
        {
          "language": "cpp",
          "problem": "A1",
          "status": true,
          "summary": {
            "max_time_ms": 33,
            "max_memory_kb": 256
          },
          "time": "2025-08-11T02:57:20.045Z",
          "resultDescription": "❌ RTE — Runtime Error",
          "problemName": "Tính Giai Thừa",
          "maxPoints": 0
        },
        {
          "language": "cpp",
          "problem": "A1",
          "status": true,
          "summary": {
            "max_time_ms": 23,
            "max_memory_kb": 256
          },
          "time": "2025-08-11T02:56:51.487Z",
          "resultDescription": "❌ RTE — Runtime Error",
          "problemName": "Tính Giai Thừa",
          "maxPoints": 0
        },
        {
          "language": "cpp",
          "problem": "A1",
          "status": true,
          "summary": {
            "max_time_ms": 45,
            "max_memory_kb": 256
          },
          "time": "2025-08-11T02:56:48.903Z",
          "resultDescription": "❌ RTE — Runtime Error",
          "problemName": "Tính Giai Thừa",
          "maxPoints": 0
        },
        {
          "language": "cpp",
          "problem": "A1",
          "status": true,
          "summary": {
            "max_time_ms": 26,
            "max_memory_kb": 256
          },
          "time": "2025-08-11T02:56:46.252Z",
          "resultDescription": "❌ RTE — Runtime Error",
          "problemName": "Tính Giai Thừa",
          "maxPoints": 0
        },
        {
          "language": "cpp",
          "problem": "A1",
          "status": true,
          "summary": {
            "max_time_ms": 23,
            "max_memory_kb": 256
          },
          "time": "2025-08-11T02:56:43.993Z",
          "resultDescription": "❌ RTE — Runtime Error",
          "problemName": "Tính Giai Thừa",
          "maxPoints": 0
        },
        {
          "language": "cpp",
          "problem": "A1",
          "status": true,
          "summary": {
            "max_time_ms": 25,
            "max_memory_kb": 256
          },
          "time": "2025-08-11T02:56:41.380Z",
          "resultDescription": "❌ RTE — Runtime Error",
          "problemName": "Tính Giai Thừa",
          "maxPoints": 0
        },
        {
          "language": "cpp",
          "problem": "A1",
          "status": true,
          "summary": {
            "max_time_ms": 30,
            "max_memory_kb": 256
          },
          "time": "2025-08-11T02:56:38.805Z",
          "resultDescription": "❌ RTE — Runtime Error",
          "problemName": "Tính Giai Thừa",
          "maxPoints": 0
        },
        {
          "language": "cpp",
          "problem": "A1",
          "status": true,
          "summary": {
            "max_time_ms": 31,
            "max_memory_kb": 256
          },
          "time": "2025-08-11T02:56:36.204Z",
          "resultDescription": "❌ RTE — Runtime Error",
          "problemName": "Tính Giai Thừa",
          "maxPoints": 0
        },
        {
          "language": "cpp",
          "problem": "A1",
          "status": true,
          "summary": {
            "max_time_ms": 23,
            "max_memory_kb": 256
          },
          "time": "2025-08-11T02:56:33.203Z",
          "resultDescription": "❌ RTE — Runtime Error",
          "problemName": "Tính Giai Thừa",
          "maxPoints": 0
        },
        {
          "language": "cpp",
          "problem": "A1",
          "status": true,
          "summary": {
            "max_time_ms": 26,
            "max_memory_kb": 256
          },
          "time": "2025-08-11T02:56:30.237Z",
          "resultDescription": "❌ RTE — Runtime Error",
          "problemName": "Tính Giai Thừa",
          "maxPoints": 0
        },
        {
          "language": "cpp",
          "problem": "A1",
          "status": true,
          "summary": {
            "max_time_ms": 27,
            "max_memory_kb": 256
          },
          "time": "2025-08-11T02:56:27.681Z",
          "resultDescription": "❌ RTE — Runtime Error",
          "problemName": "Tính Giai Thừa",
          "maxPoints": 0
        },
        {
          "language": "cpp",
          "problem": "A1",
          "status": true,
          "summary": {
            "max_time_ms": 28,
            "max_memory_kb": 256
          },
          "time": "2025-08-11T02:56:16.779Z",
          "resultDescription": "❌ RTE — Runtime Error",
          "problemName": "Tính Giai Thừa",
          "maxPoints": 0
        },
        {
          "language": "cpp",
          "problem": "A1",
          "status": true,
          "summary": {
            "max_time_ms": 20,
            "max_memory_kb": 256
          },
          "time": "2025-08-11T02:56:14.048Z",
          "resultDescription": "❌ RTE — Runtime Error",
          "problemName": "Tính Giai Thừa",
          "maxPoints": 0
        },
        {
          "language": "cpp",
          "problem": "A1",
          "status": true,
          "summary": {
            "max_time_ms": 31,
            "max_memory_kb": 256
          },
          "time": "2025-08-11T02:56:10.778Z",
          "resultDescription": "❌ RTE — Runtime Error",
          "problemName": "Tính Giai Thừa",
          "maxPoints": 0
        },
        {
          "language": "cpp",
          "problem": "A1",
          "status": true,
          "summary": {
            "max_time_ms": 23,
            "max_memory_kb": 256
          },
          "time": "2025-08-11T02:56:07.882Z",
          "resultDescription": "❌ RTE — Runtime Error",
          "problemName": "Tính Giai Thừa",
          "maxPoints": 0
        },
        {
          "language": "cpp",
          "problem": "A1",
          "status": true,
          "summary": {
            "max_time_ms": 30,
            "max_memory_kb": 256
          },
          "time": "2025-08-11T02:56:04.581Z",
          "resultDescription": "❌ RTE — Runtime Error",
          "problemName": "Tính Giai Thừa",
          "maxPoints": 0
        },
        {
          "language": "cpp",
          "problem": "A1",
          "status": true,
          "summary": {
            "max_time_ms": 23,
            "max_memory_kb": 256
          },
          "time": "2025-08-11T02:56:01.966Z",
          "resultDescription": "❌ RTE — Runtime Error",
          "problemName": "Tính Giai Thừa",
          "maxPoints": 0
        },
        {
          "language": "cpp",
          "problem": "A1",
          "status": true,
          "summary": {
            "max_time_ms": 24,
            "max_memory_kb": 256
          },
          "time": "2025-08-11T02:55:59.086Z",
          "resultDescription": "❌ RTE — Runtime Error",
          "problemName": "Tính Giai Thừa",
          "maxPoints": 0
        },
        {
          "language": "cpp",
          "problem": "A1",
          "status": true,
          "summary": {
            "max_time_ms": 28,
            "max_memory_kb": 256
          },
          "time": "2025-08-11T02:55:56.505Z",
          "resultDescription": "❌ RTE — Runtime Error",
          "problemName": "Tính Giai Thừa",
          "maxPoints": 0
        },
        {
          "language": "cpp",
          "problem": "A1",
          "status": true,
          "summary": {
            "max_time_ms": 27,
            "max_memory_kb": 256
          },
          "time": "2025-08-11T02:55:53.193Z",
          "resultDescription": "❌ RTE — Runtime Error",
          "problemName": "Tính Giai Thừa",
          "maxPoints": 0
        },
        {
          "language": "cpp",
          "problem": "A1",
          "status": true,
          "summary": {
            "max_time_ms": 28,
            "max_memory_kb": 256
          },
          "time": "2025-08-11T02:55:30.325Z",
          "resultDescription": "❌ RTE — Runtime Error",
          "problemName": "Tính Giai Thừa",
          "maxPoints": 0
        },
        {
          "language": "cpp",
          "problem": "A1",
          "status": true,
          "summary": {
            "max_time_ms": 36,
            "max_memory_kb": 256
          },
          "time": "2025-08-11T02:55:08.186Z",
          "resultDescription": "❌ RTE — Runtime Error",
          "problemName": "Tính Giai Thừa",
          "maxPoints": 0
        },
        {
          "language": "cpp",
          "problem": "A1",
          "status": true,
          "summary": {
            "max_time_ms": 30,
            "max_memory_kb": 256
          },
          "time": "2025-08-11T02:54:45.210Z",
          "resultDescription": "❌ RTE — Runtime Error",
          "problemName": "Tính Giai Thừa",
          "maxPoints": 0
        },
        {
          "language": "cpp",
          "problem": "A1",
          "status": true,
          "summary": {
            "max_time_ms": 33,
            "max_memory_kb": 256
          },
          "time": "2025-08-11T02:54:35.589Z",
          "resultDescription": "❌ RTE — Runtime Error",
          "problemName": "Tính Giai Thừa",
          "maxPoints": 0
        },
        {
          "language": "cpp",
          "problem": "A1",
          "status": true,
          "summary": {
            "max_time_ms": 27,
            "max_memory_kb": 256
          },
          "time": "2025-08-11T02:54:32.727Z",
          "resultDescription": "❌ RTE — Runtime Error",
          "problemName": "Tính Giai Thừa",
          "maxPoints": 0
        },
        {
          "language": "cpp",
          "problem": "A1",
          "status": true,
          "summary": {
            "max_time_ms": 31,
            "max_memory_kb": 256
          },
          "time": "2025-08-11T02:54:28.241Z",
          "resultDescription": "❌ RTE — Runtime Error",
          "problemName": "Tính Giai Thừa",
          "maxPoints": 0
        },
        {
          "language": "cpp",
          "problem": "A1",
          "status": true,
          "summary": {
            "max_time_ms": 42,
            "max_memory_kb": 256
          },
          "time": "2025-08-11T02:54:25.478Z",
          "resultDescription": "❌ RTE — Runtime Error",
          "problemName": "Tính Giai Thừa",
          "maxPoints": 0
        },
        {
          "language": "cpp",
          "problem": "A1",
          "status": true,
          "summary": {
            "max_time_ms": 21,
            "max_memory_kb": 256
          },
          "time": "2025-08-11T02:52:37.235Z",
          "resultDescription": "❌ RTE — Runtime Error",
          "problemName": "Tính Giai Thừa",
          "maxPoints": 0
        },
        {
          "language": "cpp",
          "problem": "A1",
          "status": true,
          "summary": {
            "max_time_ms": 33,
            "max_memory_kb": 256
          },
          "time": "2025-08-11T02:52:33.834Z",
          "resultDescription": "❌ RTE — Runtime Error",
          "problemName": "Tính Giai Thừa",
          "maxPoints": 0
        },
        {
          "language": "cpp",
          "problem": "A1",
          "status": true,
          "summary": {
            "max_time_ms": 27,
            "max_memory_kb": 256
          },
          "time": "2025-08-11T02:52:30.449Z",
          "resultDescription": "❌ RTE — Runtime Error",
          "problemName": "Tính Giai Thừa",
          "maxPoints": 0
        },
        {
          "language": "cpp",
          "problem": "A1",
          "status": true,
          "summary": {
            "max_time_ms": 29,
            "max_memory_kb": 256
          },
          "time": "2025-08-11T02:52:27.096Z",
          "resultDescription": "❌ RTE — Runtime Error",
          "problemName": "Tính Giai Thừa",
          "maxPoints": 0
        },
        {
          "language": "cpp",
          "problem": "A1",
          "status": true,
          "summary": {
            "max_time_ms": 26,
            "max_memory_kb": 256
          },
          "time": "2025-08-11T02:52:14.575Z",
          "resultDescription": "❌ RTE — Runtime Error",
          "problemName": "Tính Giai Thừa",
          "maxPoints": 0
        },
        {
          "language": "cpp",
          "problem": "A1",
          "status": true,
          "summary": {
            "max_time_ms": 23,
            "max_memory_kb": 256
          },
          "time": "2025-08-11T02:52:11.230Z",
          "resultDescription": "❌ RTE — Runtime Error",
          "problemName": "Tính Giai Thừa",
          "maxPoints": 0
        },
        {
          "language": "cpp",
          "problem": "A1",
          "status": true,
          "summary": {
            "max_time_ms": 31,
            "max_memory_kb": 256
          },
          "time": "2025-08-11T02:52:07.774Z",
          "resultDescription": "❌ RTE — Runtime Error",
          "problemName": "Tính Giai Thừa",
          "maxPoints": 0
        },
        {
          "language": "cpp",
          "problem": "A1",
          "status": true,
          "summary": {
            "max_time_ms": 29,
            "max_memory_kb": 256
          },
          "time": "2025-08-11T02:52:04.377Z",
          "resultDescription": "❌ RTE — Runtime Error",
          "problemName": "Tính Giai Thừa",
          "maxPoints": 0
        },
        {
          "language": "cpp",
          "problem": "A1",
          "status": true,
          "summary": {
            "max_time_ms": 27,
            "max_memory_kb": 256
          },
          "time": "2025-08-11T02:52:00.866Z",
          "resultDescription": "❌ RTE — Runtime Error",
          "problemName": "Tính Giai Thừa",
          "maxPoints": 0
        },
        {
          "language": "cpp",
          "problem": "A1",
          "status": true,
          "summary": {
            "max_time_ms": 27,
            "max_memory_kb": 256
          },
          "time": "2025-08-11T02:51:57.496Z",
          "resultDescription": "❌ RTE — Runtime Error",
          "problemName": "Tính Giai Thừa",
          "maxPoints": 0
        },
        {
          "language": "cpp",
          "problem": "A1",
          "status": true,
          "summary": {
            "max_time_ms": 25,
            "max_memory_kb": 256
          },
          "time": "2025-08-11T02:51:54.066Z",
          "resultDescription": "❌ RTE — Runtime Error",
          "problemName": "Tính Giai Thừa",
          "maxPoints": 0
        },
        {
          "language": "cpp",
          "problem": "A1",
          "status": true,
          "summary": {
            "max_time_ms": 28,
            "max_memory_kb": 256
          },
          "time": "2025-08-11T02:51:50.824Z",
          "resultDescription": "❌ RTE — Runtime Error",
          "problemName": "Tính Giai Thừa",
          "maxPoints": 0
        },
        {
          "language": "cpp",
          "problem": "A1",
          "status": true,
          "summary": {
            "max_time_ms": 24,
            "max_memory_kb": 256
          },
          "time": "2025-08-11T02:51:46.854Z",
          "resultDescription": "❌ RTE — Runtime Error",
          "problemName": "Tính Giai Thừa",
          "maxPoints": 0
        },
        {
          "language": "cpp",
          "problem": "A1",
          "status": true,
          "summary": {
            "max_time_ms": 24,
            "max_memory_kb": 256
          },
          "time": "2025-08-11T02:51:42.675Z",
          "resultDescription": "❌ RTE — Runtime Error",
          "problemName": "Tính Giai Thừa",
          "maxPoints": 0
        },
        {
          "language": "cpp",
          "problem": "A1",
          "status": true,
          "summary": {
            "max_time_ms": 28,
            "max_memory_kb": 256
          },
          "time": "2025-08-11T02:51:39.356Z",
          "resultDescription": "❌ RTE — Runtime Error",
          "problemName": "Tính Giai Thừa",
          "maxPoints": 0
        },
        {
          "language": "cpp",
          "problem": "A1",
          "status": true,
          "summary": {
            "max_time_ms": 27,
            "max_memory_kb": 256
          },
          "time": "2025-08-11T02:51:35.361Z",
          "resultDescription": "❌ RTE — Runtime Error",
          "problemName": "Tính Giai Thừa",
          "maxPoints": 0
        },
        {
          "language": "cpp",
          "problem": "A1",
          "status": true,
          "summary": {
            "max_time_ms": 25,
            "max_memory_kb": 256
          },
          "time": "2025-08-11T02:51:32.026Z",
          "resultDescription": "❌ RTE — Runtime Error",
          "problemName": "Tính Giai Thừa",
          "maxPoints": 0
        },
        {
          "language": "cpp",
          "problem": "A1",
          "status": true,
          "summary": {
            "max_time_ms": 18,
            "max_memory_kb": 256
          },
          "time": "2025-08-11T02:51:28.592Z",
          "resultDescription": "❌ RTE — Runtime Error",
          "problemName": "Tính Giai Thừa",
          "maxPoints": 0
        },
        {
          "language": "cpp",
          "problem": "A1",
          "status": true,
          "summary": {
            "max_time_ms": 23,
            "max_memory_kb": 256
          },
          "time": "2025-08-11T02:51:25.211Z",
          "resultDescription": "❌ RTE — Runtime Error",
          "problemName": "Tính Giai Thừa",
          "maxPoints": 0
        },
        {
          "language": "cpp",
          "problem": "A1",
          "status": true,
          "summary": {
            "max_time_ms": 29,
            "max_memory_kb": 256
          },
          "time": "2025-08-11T02:51:21.156Z",
          "resultDescription": "❌ RTE — Runtime Error",
          "problemName": "Tính Giai Thừa",
          "maxPoints": 0
        },
        {
          "language": "cpp",
          "problem": "A1",
          "status": true,
          "summary": {
            "max_time_ms": 116,
            "max_memory_kb": 256
          },
          "time": "2025-08-11T02:51:17.636Z",
          "resultDescription": "❌ RTE — Runtime Error",
          "problemName": "Tính Giai Thừa",
          "maxPoints": 0
        },
        {
          "language": "cpp",
          "problem": "A1",
          "status": true,
          "summary": {
            "max_time_ms": 33,
            "max_memory_kb": 256
          },
          "time": "2025-08-11T02:51:14.552Z",
          "resultDescription": "❌ RTE — Runtime Error",
          "problemName": "Tính Giai Thừa",
          "maxPoints": 0
        },
        {
          "language": "cpp",
          "problem": "A1",
          "status": true,
          "summary": {
            "max_time_ms": 37,
            "max_memory_kb": 256
          },
          "time": "2025-08-11T02:51:11.125Z",
          "resultDescription": "❌ RTE — Runtime Error",
          "problemName": "Tính Giai Thừa",
          "maxPoints": 0
        },
        {
          "language": "cpp",
          "problem": "A1",
          "status": true,
          "summary": {
            "max_time_ms": 27,
            "max_memory_kb": 256
          },
          "time": "2025-08-11T02:51:07.727Z",
          "resultDescription": "❌ RTE — Runtime Error",
          "problemName": "Tính Giai Thừa",
          "maxPoints": 0
        },
        {
          "language": "cpp",
          "problem": "A1",
          "status": true,
          "summary": {
            "max_time_ms": 35,
            "max_memory_kb": 256
          },
          "time": "2025-08-11T02:51:04.298Z",
          "resultDescription": "❌ RTE — Runtime Error",
          "problemName": "Tính Giai Thừa",
          "maxPoints": 0
        },
        {
          "language": "cpp",
          "problem": "A1",
          "status": true,
          "summary": {
            "max_time_ms": 32,
            "max_memory_kb": 256
          },
          "time": "2025-08-11T02:50:59.308Z",
          "resultDescription": "❌ RTE — Runtime Error",
          "problemName": "Tính Giai Thừa",
          "maxPoints": 0
        },
        {
          "language": "cpp",
          "problem": "A1",
          "status": true,
          "summary": {
            "max_time_ms": 33,
            "max_memory_kb": 128
          },
          "time": "2025-08-11T02:50:56.500Z",
          "resultDescription": "❌ RTE — Runtime Error",
          "problemName": "Tính Giai Thừa",
          "maxPoints": 0
        },
        {
          "language": "cpp",
          "problem": "A1",
          "status": true,
          "summary": {
            "max_time_ms": 28,
            "max_memory_kb": 256
          },
          "time": "2025-08-11T02:50:53.018Z",
          "resultDescription": "❌ RTE — Runtime Error",
          "problemName": "Tính Giai Thừa",
          "maxPoints": 0
        },
        {
          "language": "cpp",
          "problem": "A1",
          "status": true,
          "summary": {
            "max_time_ms": 35,
            "max_memory_kb": 256
          },
          "time": "2025-08-11T02:50:48.411Z",
          "resultDescription": "❌ RTE — Runtime Error",
          "problemName": "Tính Giai Thừa",
          "maxPoints": 0
        },
        {
          "language": "cpp",
          "problem": "A1",
          "status": true,
          "summary": {
            "max_time_ms": 35,
            "max_memory_kb": 256
          },
          "time": "2025-08-11T02:50:44.313Z",
          "resultDescription": "❌ RTE — Runtime Error",
          "problemName": "Tính Giai Thừa",
          "maxPoints": 0
        },
        {
          "language": "cpp",
          "problem": "A1",
          "status": true,
          "summary": {
            "max_time_ms": 23,
            "max_memory_kb": 256
          },
          "time": "2025-08-11T02:41:27.541Z",
          "resultDescription": "❌ RTE — Runtime Error",
          "problemName": "Tính Giai Thừa",
          "maxPoints": 0
        },
        {
          "language": "cpp",
          "problem": "A1",
          "status": true,
          "summary": {
            "max_time_ms": 28,
            "max_memory_kb": 256
          },
          "time": "2025-08-11T02:41:25.343Z",
          "resultDescription": "❌ RTE — Runtime Error",
          "problemName": "Tính Giai Thừa",
          "maxPoints": 0
        },
        {
          "language": "cpp",
          "problem": "A1",
          "status": true,
          "summary": {
            "max_time_ms": 29,
            "max_memory_kb": 256
          },
          "time": "2025-08-11T02:41:22.940Z",
          "resultDescription": "❌ RTE — Runtime Error",
          "problemName": "Tính Giai Thừa",
          "maxPoints": 0
        },
        {
          "language": "cpp",
          "problem": "A1",
          "status": true,
          "summary": {
            "max_time_ms": 32,
            "max_memory_kb": 256
          },
          "time": "2025-08-11T02:41:20.580Z",
          "resultDescription": "❌ RTE — Runtime Error",
          "problemName": "Tính Giai Thừa",
          "maxPoints": 0
        },
        {
          "language": "cpp",
          "problem": "A1",
          "status": true,
          "summary": {
            "max_time_ms": 28,
            "max_memory_kb": 256
          },
          "time": "2025-08-11T02:41:18.534Z",
          "resultDescription": "❌ RTE — Runtime Error",
          "problemName": "Tính Giai Thừa",
          "maxPoints": 0
        },
        {
          "language": "cpp",
          "problem": "A1",
          "status": true,
          "summary": {
            "max_time_ms": 31,
            "max_memory_kb": 256
          },
          "time": "2025-08-11T02:41:16.087Z",
          "resultDescription": "❌ RTE — Runtime Error",
          "problemName": "Tính Giai Thừa",
          "maxPoints": 0
        },
        {
          "language": "cpp",
          "problem": "A1",
          "status": true,
          "summary": {
            "max_time_ms": 23,
            "max_memory_kb": 256
          },
          "time": "2025-08-11T02:41:13.589Z",
          "resultDescription": "❌ RTE — Runtime Error",
          "problemName": "Tính Giai Thừa",
          "maxPoints": 0
        },
        {
          "language": "cpp",
          "problem": "A1",
          "status": true,
          "summary": {
            "max_time_ms": 38,
            "max_memory_kb": 256
          },
          "time": "2025-08-11T02:41:11.158Z",
          "resultDescription": "❌ RTE — Runtime Error",
          "problemName": "Tính Giai Thừa",
          "maxPoints": 0
        },
        {
          "language": "cpp",
          "problem": "A1",
          "status": true,
          "summary": {
            "max_time_ms": 28,
            "max_memory_kb": 256
          },
          "time": "2025-08-11T02:41:08.739Z",
          "resultDescription": "❌ RTE — Runtime Error",
          "problemName": "Tính Giai Thừa",
          "maxPoints": 0
        },
        {
          "language": "cpp",
          "problem": "A1",
          "status": true,
          "summary": {
            "max_time_ms": 24,
            "max_memory_kb": 256
          },
          "time": "2025-08-11T02:41:06.517Z",
          "resultDescription": "❌ RTE — Runtime Error",
          "problemName": "Tính Giai Thừa",
          "maxPoints": 0
        },
        {
          "language": "cpp",
          "problem": "A1",
          "status": true,
          "summary": {
            "max_time_ms": 22,
            "max_memory_kb": 256
          },
          "time": "2025-08-11T02:41:04.145Z",
          "resultDescription": "❌ RTE — Runtime Error",
          "problemName": "Tính Giai Thừa",
          "maxPoints": 0
        },
        {
          "language": "cpp",
          "problem": "A1",
          "status": true,
          "summary": {
            "max_time_ms": 30,
            "max_memory_kb": 256
          },
          "time": "2025-08-11T02:41:01.587Z",
          "resultDescription": "❌ RTE — Runtime Error",
          "problemName": "Tính Giai Thừa",
          "maxPoints": 0
        },
        {
          "language": "cpp",
          "problem": "A1",
          "status": true,
          "summary": {
            "max_time_ms": 32,
            "max_memory_kb": 256
          },
          "time": "2025-08-11T02:40:59.178Z",
          "resultDescription": "❌ RTE — Runtime Error",
          "problemName": "Tính Giai Thừa",
          "maxPoints": 0
        },
        {
          "language": "cpp",
          "problem": "A1",
          "status": true,
          "summary": {
            "max_time_ms": 38,
            "max_memory_kb": 256
          },
          "time": "2025-08-11T02:40:56.669Z",
          "resultDescription": "❌ RTE — Runtime Error",
          "problemName": "Tính Giai Thừa",
          "maxPoints": 0
        },
        {
          "language": "cpp",
          "problem": "A1",
          "status": true,
          "summary": {
            "max_time_ms": 29,
            "max_memory_kb": 256
          },
          "time": "2025-08-11T02:40:54.169Z",
          "resultDescription": "❌ RTE — Runtime Error",
          "problemName": "Tính Giai Thừa",
          "maxPoints": 0
        },
        {
          "language": "cpp",
          "problem": "A1",
          "status": true,
          "summary": {
            "max_time_ms": 25,
            "max_memory_kb": 256
          },
          "time": "2025-08-11T02:40:51.399Z",
          "resultDescription": "❌ RTE — Runtime Error",
          "problemName": "Tính Giai Thừa",
          "maxPoints": 0
        },
        {
          "language": "cpp",
          "problem": "A1",
          "status": true,
          "summary": {
            "max_time_ms": 53,
            "max_memory_kb": 256
          },
          "time": "2025-08-11T02:40:48.997Z",
          "resultDescription": "❌ RTE — Runtime Error",
          "problemName": "Tính Giai Thừa",
          "maxPoints": 0
        },
        {
          "language": "cpp",
          "problem": "A1",
          "status": true,
          "summary": {
            "max_time_ms": 27,
            "max_memory_kb": 256
          },
          "time": "2025-08-11T02:40:46.579Z",
          "resultDescription": "❌ RTE — Runtime Error",
          "problemName": "Tính Giai Thừa",
          "maxPoints": 0
        },
        {
          "language": "cpp",
          "problem": "A1",
          "status": true,
          "summary": {
            "max_time_ms": 30,
            "max_memory_kb": 256
          },
          "time": "2025-08-11T02:40:44.164Z",
          "resultDescription": "❌ RTE — Runtime Error",
          "problemName": "Tính Giai Thừa",
          "maxPoints": 0
        },
        {
          "language": "cpp",
          "problem": "A1",
          "status": true,
          "summary": {
            "max_time_ms": 37,
            "max_memory_kb": 256
          },
          "time": "2025-08-11T02:40:42.044Z",
          "resultDescription": "❌ RTE — Runtime Error",
          "problemName": "Tính Giai Thừa",
          "maxPoints": 0
        },
        {
          "language": "cpp",
          "problem": "A1",
          "status": true,
          "summary": {
            "max_time_ms": 21,
            "max_memory_kb": 256
          },
          "time": "2025-08-11T02:40:38.021Z",
          "resultDescription": "❌ RTE — Runtime Error",
          "problemName": "Tính Giai Thừa",
          "maxPoints": 0
        },
        {
          "language": "cpp",
          "problem": "A1",
          "status": true,
          "summary": {
            "max_time_ms": 28,
            "max_memory_kb": 256
          },
          "time": "2025-08-11T02:40:21.831Z",
          "resultDescription": "❌ RTE — Runtime Error",
          "problemName": "Tính Giai Thừa",
          "maxPoints": 0
        },
        {
          "language": "cpp",
          "problem": "A1",
          "status": true,
          "summary": {
            "max_time_ms": 27,
            "max_memory_kb": 256
          },
          "time": "2025-08-11T02:40:19.587Z",
          "resultDescription": "❌ RTE — Runtime Error",
          "problemName": "Tính Giai Thừa",
          "maxPoints": 0
        },
        {
          "language": "cpp",
          "problem": "A1",
          "status": true,
          "summary": {
            "max_time_ms": 24,
            "max_memory_kb": 256
          },
          "time": "2025-08-11T02:39:31.012Z",
          "resultDescription": "❌ RTE — Runtime Error",
          "problemName": "Tính Giai Thừa",
          "maxPoints": 0
        },
        {
          "language": "cpp",
          "problem": "A1",
          "status": true,
          "summary": {
            "max_time_ms": 47,
            "max_memory_kb": 256
          },
          "time": "2025-08-11T02:39:28.235Z",
          "resultDescription": "❌ RTE — Runtime Error",
          "problemName": "Tính Giai Thừa",
          "maxPoints": 0
        },
        {
          "language": "cpp",
          "problem": "A1",
          "status": true,
          "summary": {
            "max_time_ms": 29,
            "max_memory_kb": 256
          },
          "time": "2025-08-11T02:39:25.624Z",
          "resultDescription": "❌ RTE — Runtime Error",
          "problemName": "Tính Giai Thừa",
          "maxPoints": 0
        },
        {
          "language": "cpp",
          "problem": "A1",
          "status": true,
          "summary": {
            "max_time_ms": 24,
            "max_memory_kb": 256
          },
          "time": "2025-08-11T02:39:21.853Z",
          "resultDescription": "❌ RTE — Runtime Error",
          "problemName": "Tính Giai Thừa",
          "maxPoints": 0
        },
        {
          "language": "cpp",
          "problem": "A1",
          "status": true,
          "summary": {
            "max_time_ms": 26,
            "max_memory_kb": 256
          },
          "time": "2025-08-11T02:39:19.094Z",
          "resultDescription": "❌ RTE — Runtime Error",
          "problemName": "Tính Giai Thừa",
          "maxPoints": 0
        },
        {
          "language": "cpp",
          "problem": "A1",
          "status": true,
          "summary": {
            "max_time_ms": 28,
            "max_memory_kb": 256
          },
          "time": "2025-08-11T02:39:16.314Z",
          "resultDescription": "❌ RTE — Runtime Error",
          "problemName": "Tính Giai Thừa",
          "maxPoints": 0
        },
        {
          "language": "cpp",
          "problem": "A1",
          "status": true,
          "summary": {
            "max_time_ms": 28,
            "max_memory_kb": 256
          },
          "time": "2025-08-11T02:39:13.484Z",
          "resultDescription": "❌ RTE — Runtime Error",
          "problemName": "Tính Giai Thừa",
          "maxPoints": 0
        },
        {
          "language": "cpp",
          "problem": "A1",
          "status": true,
          "summary": {
            "max_time_ms": 35,
            "max_memory_kb": 256
          },
          "time": "2025-08-11T02:39:09.979Z",
          "resultDescription": "❌ RTE — Runtime Error",
          "problemName": "Tính Giai Thừa",
          "maxPoints": 0
        },
        {
          "language": "cpp",
          "problem": "A1",
          "status": true,
          "summary": {
            "max_time_ms": 35,
            "max_memory_kb": 256
          },
          "time": "2025-08-11T02:39:06.687Z",
          "resultDescription": "❌ RTE — Runtime Error",
          "problemName": "Tính Giai Thừa",
          "maxPoints": 0
        },
        {
          "language": "cpp",
          "problem": "A1",
          "status": true,
          "summary": {
            "max_time_ms": 26,
            "max_memory_kb": 256
          },
          "time": "2025-08-11T02:39:03.316Z",
          "resultDescription": "❌ RTE — Runtime Error",
          "problemName": "Tính Giai Thừa",
          "maxPoints": 0
        },
        {
          "language": "cpp",
          "problem": "A1",
          "status": true,
          "summary": {
            "max_time_ms": 23,
            "max_memory_kb": 256
          },
          "time": "2025-08-11T02:39:00.672Z",
          "resultDescription": "❌ RTE — Runtime Error",
          "problemName": "Tính Giai Thừa",
          "maxPoints": 0
        },
        {
          "language": "cpp",
          "problem": "A1",
          "status": true,
          "summary": {
            "max_time_ms": 36,
            "max_memory_kb": 256
          },
          "time": "2025-08-11T02:38:58.037Z",
          "resultDescription": "❌ RTE — Runtime Error",
          "problemName": "Tính Giai Thừa",
          "maxPoints": 0
        },
        {
          "language": "c",
          "problem": "A1",
          "status": true,
          "summary": {
            "max_time_ms": 2000,
            "max_memory_kb": 0
          },
          "time": "2025-08-11T02:37:22.546Z",
          "resultDescription": "❌ TLE — Time Limit Exceeded",
          "problemName": "Tính Giai Thừa",
          "maxPoints": 0
        },
        {
          "language": "c",
          "problem": "A1",
          "status": true,
          "summary": {
            "max_time_ms": 2000,
            "max_memory_kb": 384
          },
          "time": "2025-08-11T02:12:40.771Z",
          "resultDescription": "❌ TLE — Time Limit Exceeded",
          "problemName": "Tính Giai Thừa",
          "maxPoints": 0
        }
      ],
      "RecentAttempts": [
        {
          "language": "cpp",
          "problem": "A1",
          "status": true,
          "summary": {
            "max_time_ms": 26,
            "max_memory_kb": 256
          },
          "time": "2025-08-11T02:59:06.538Z",
          "resultDescription": "❌ RTE — Runtime Error",
          "problemName": "Tính Giai Thừa",
          "maxPoints": 0
        }
      ],
      "Data": []
    },
    {
      "idData": "U002",
      "Points": 0,
      "History": [],
      "RecentAttempts": [],
      "Data": []
    },
    {
      "idData": "U003",
      "Points": 100,
      "History": [
        {
          "language": "c",
          "problem": "A1",
          "status": true,
          "summary": {
            "max_time_ms": 27,
            "max_memory_kb": 512
          },
          "time": "2025-08-11T14:03:54.882Z",
          "resultDescription": "✅ AC — Passed all: 20/20",
          "problemName": "Tính Giai Thừa",
          "maxPoints": 100
        },
        {
          "language": "py",
          "problem": "B1",
          "status": true,
          "summary": {
            "max_time_ms": 93,
            "max_memory_kb": 640
          },
          "time": "2025-08-11T02:14:44.537Z",
          "resultDescription": "❌ RTE — Runtime Error",
          "problemName": "Sắp Xếp Hai Mảng",
          "maxPoints": 0
        }
      ],
      "RecentAttempts": [
        {
          "language": "py",
          "problem": "B1",
          "status": true,
          "summary": {
            "max_time_ms": 93,
            "max_memory_kb": 640
          },
          "time": "2025-08-11T02:14:44.537Z",
          "resultDescription": "❌ RTE — Runtime Error",
          "problemName": "Sắp Xếp Hai Mảng",
          "maxPoints": 0
        },
        {
          "language": "c",
          "problem": "A1",
          "status": true,
          "summary": {
            "max_time_ms": 27,
            "max_memory_kb": 512
          },
          "time": "2025-08-11T14:03:54.882Z",
          "resultDescription": "✅ AC — Passed all: 20/20",
          "problemName": "Tính Giai Thừa",
          "maxPoints": 100
        }
      ],
      "Data": []
    },
    {
      "idData": "U004",
      "Points": 0,
      "History": [],
      "RecentAttempts": [],
      "Data": []
    },
    {
      "idData": "U005",
      "Points": 250,
      "History": [
        {
          "language": "c",
          "problem": "B1",
          "status": true,
          "summary": {
            "max_time_ms": 28,
            "max_memory_kb": 512
          },
          "time": "2025-08-11T14:11:24.471Z",
          "resultDescription": "✅ AC — Passed all: 20/20",
          "problemName": "Sắp Xếp Hai Mảng",
          "maxPoints": 150
        },
        {
          "language": "c",
          "problem": "B1",
          "status": true,
          "summary": {
            "max_time_ms": 34,
            "max_memory_kb": 512
          },
          "time": "2025-08-11T14:07:36.214Z",
          "resultDescription": "❌ WA — Passed 0/20",
          "problemName": "Sắp Xếp Hai Mảng",
          "maxPoints": 0
        },
        {
          "language": "c",
          "problem": "B1",
          "status": true,
          "summary": {
            "max_time_ms": 38,
            "max_memory_kb": 512
          },
          "time": "2025-08-11T14:06:11.228Z",
          "resultDescription": "❌ WA — Passed 0/20",
          "problemName": "Sắp Xếp Hai Mảng",
          "maxPoints": 0
        },
        {
          "language": "c",
          "problem": "A1",
          "status": true,
          "summary": {
            "max_time_ms": 31,
            "max_memory_kb": 512
          },
          "time": "2025-08-11T14:05:51.026Z",
          "resultDescription": "✅ AC — Passed all: 20/20",
          "problemName": "Tính Giai Thừa",
          "maxPoints": 100
        }
      ],
      "RecentAttempts": [
        {
          "language": "c",
          "problem": "A1",
          "status": true,
          "summary": {
            "max_time_ms": 31,
            "max_memory_kb": 512
          },
          "time": "2025-08-11T14:05:51.026Z",
          "resultDescription": "✅ AC — Passed all: 20/20",
          "problemName": "Tính Giai Thừa",
          "maxPoints": 100
        },
        {
          "language": "c",
          "problem": "B1",
          "status": true,
          "summary": {
            "max_time_ms": 28,
            "max_memory_kb": 512
          },
          "time": "2025-08-11T14:11:24.471Z",
          "resultDescription": "✅ AC — Passed all: 20/20",
          "problemName": "Sắp Xếp Hai Mảng",
          "maxPoints": 150
        }
      ],
      "Data": []
    }
  ]
}